steosmorphy/__init__.py
steosmorphy/morph.dawg.zst
steosmorphy/steosmorphy.dll
steosmorphy/steosmorphy_lib.py
steosmorphy-1.0.1.dist-info/licenses/LICENSE
steosmorphy-1.0.1.dist-info/METADATA
steosmorphy-1.0.1.dist-info/WHEEL
steosmorphy-1.0.1.dist-info/top_level.txt
steosmorphy-1.0.1.dist-info/RECORD
