Metadata-Version: 2.4
Name: steosmorphy
Version: 1.0.1
Summary: Высокопроизводительный морфологический анализатор для Python
Home-page: https://github.com/SteosOfficial/SteosMorphy-py
Author: Steos
Author-email: regger@mind-simulation.com
Classifier: Programming Language :: Python :: 3
Classifier: Programming Language :: Go
Classifier: License :: OSI Approved :: MIT License
Classifier: Operating System :: OS Independent
Classifier: Topic :: Text Processing :: Linguistic
Requires-Python: >=3.7
License-File: LICENSE
Requires-Dist: zstandard
Requires-Dist: tqdm
Dynamic: author
Dynamic: author-email
Dynamic: classifier
Dynamic: description
Dynamic: description-content-type
Dynamic: home-page
Dynamic: license-file
Dynamic: requires-dist
Dynamic: requires-python
Dynamic: summary
